waster/__init__.py
waster-0.0.9.dist-info/LICENSE
waster-0.0.9.dist-info/METADATA
waster-0.0.9.dist-info/WHEEL
waster-0.0.9.dist-info/entry_points.txt
waster-0.0.9.dist-info/top_level.txt
waster-0.0.9.dist-info/RECORD
