Metadata-Version: 2.1
Name: waster
Version: 0.0.9
Summary: A simple microservice to test the behaviour of infrastructures.
Home-page: UNKNOWN
Author: Leikt Sol'Reihin
License: UNKNOWN
Platform: UNKNOWN
Requires-Python: >3.10.0
License-File: LICENSE
Provides-Extra: dev
Provides-Extra: doc
Requires-Dist: sphinx >=7.2.6 ; extra == 'doc'
Requires-Dist: furo >=2023.9.10 ; extra == 'doc'
Provides-Extra: test
Requires-Dist: coverage >=7.4.0 ; extra == 'test'
Requires-Dist: pytest >=7.4.4 ; extra == 'test'
